Workbook

Sheet Dashboard
A1: Resolution Nation — Roadmap Tracker
A2: Anchored to project start: 2026-06-01
A3: Target: first paying school by ~May 2027 (Month 12).
A5: Phase Summary
A6: Phase | B6: Theme | C6: Tasks | D6: Done | E6: In Progress | F6: Blocked | G6: Not Started | H6: % Done
A7: 0 | B7: Foundation & Decisions | C7: =COUNTIF('Roadmap Tasks'!B2:B102,"0") -> 10 | D7: =COUNTIFS('Roadmap Tasks'!B2:B102,"0",'Roadmap Tasks'!H2:H102,"Done") -> 2 | E7: =COUNTIFS('Roadmap Tasks'!B2:B102,"0",'Roadmap Tasks'!H2:H102,"In Progress") -> 0 | F7: =COUNTIFS('Roadmap Tasks'!B2:B102,"0",'Roadmap Tasks'!H2:H102,"Blocked") -> 0 | G7: =COUNTIFS('Roadmap Tasks'!B2:B102,"0",'Roadmap Tasks'!H2:H102,"Not Started") -> 8 | H7: =IF(C7=0,0,D7/C7) -> 0.2
A8: 1 | B8: Compliance + Hardening | C8: =COUNTIF('Roadmap Tasks'!B2:B102,"1") -> 21 | D8: =COUNTIFS('Roadmap Tasks'!B2:B102,"1",'Roadmap Tasks'!H2:H102,"Done") -> 4 | E8: =COUNTIFS('Roadmap Tasks'!B2:B102,"1",'Roadmap Tasks'!H2:H102,"In Progress") -> 7 | F8: =COUNTIFS('Roadmap Tasks'!B2:B102,"1",'Roadmap Tasks'!H2:H102,"Blocked") -> 0 | G8: =COUNTIFS('Roadmap Tasks'!B2:B102,"1",'Roadmap Tasks'!H2:H102,"Not Started") -> 10 | H8: =IF(C8=0,0,D8/C8) -> 0.19047619
A9: 2 | B9: School-Ready Features | C9: =COUNTIF('Roadmap Tasks'!B2:B102,"2") -> 18 | D9: =COUNTIFS('Roadmap Tasks'!B2:B102,"2",'Roadmap Tasks'!H2:H102,"Done") -> 0 | E9: =COUNTIFS('Roadmap Tasks'!B2:B102,"2",'Roadmap Tasks'!H2:H102,"In Progress") -> 0 | F9: =COUNTIFS('Roadmap Tasks'!B2:B102,"2",'Roadmap Tasks'!H2:H102,"Blocked") -> 0 | G9: =COUNTIFS('Roadmap Tasks'!B2:B102,"2",'Roadmap Tasks'!H2:H102,"Not Started") -> 18 | H9: =IF(C9=0,0,D9/C9) -> 0
A10: 3 | B10: Mobile Build | C10: =COUNTIF('Roadmap Tasks'!B2:B102,"3") -> 13 | D10: =COUNTIFS('Roadmap Tasks'!B2:B102,"3",'Roadmap Tasks'!H2:H102,"Done") -> 0 | E10: =COUNTIFS('Roadmap Tasks'!B2:B102,"3",'Roadmap Tasks'!H2:H102,"In Progress") -> 0 | F10: =COUNTIFS('Roadmap Tasks'!B2:B102,"3",'Roadmap Tasks'!H2:H102,"Blocked") -> 0 | G10: =COUNTIFS('Roadmap Tasks'!B2:B102,"3",'Roadmap Tasks'!H2:H102,"Not Started") -> 13 | H10: =IF(C10=0,0,D10/C10) -> 0
A11: 4 | B11: Pilot + Certification | C11: =COUNTIF('Roadmap Tasks'!B2:B102,"4") -> 15 | D11: =COUNTIFS('Roadmap Tasks'!B2:B102,"4",'Roadmap Tasks'!H2:H102,"Done") -> 0 | E11: =COUNTIFS('Roadmap Tasks'!B2:B102,"4",'Roadmap Tasks'!H2:H102,"In Progress") -> 0 | F11: =COUNTIFS('Roadmap Tasks'!B2:B102,"4",'Roadmap Tasks'!H2:H102,"Blocked") -> 0 | G11: =COUNTIFS('Roadmap Tasks'!B2:B102,"4",'Roadmap Tasks'!H2:H102,"Not Started") -> 15 | H11: =IF(C11=0,0,D11/C11) -> 0
A12: 5 | B12: App Store Submission | C12: =COUNTIF('Roadmap Tasks'!B2:B102,"5") -> 9 | D12: =COUNTIFS('Roadmap Tasks'!B2:B102,"5",'Roadmap Tasks'!H2:H102,"Done") -> 0 | E12: =COUNTIFS('Roadmap Tasks'!B2:B102,"5",'Roadmap Tasks'!H2:H102,"In Progress") -> 0 | F12: =COUNTIFS('Roadmap Tasks'!B2:B102,"5",'Roadmap Tasks'!H2:H102,"Blocked") -> 0 | G12: =COUNTIFS('Roadmap Tasks'!B2:B102,"5",'Roadmap Tasks'!H2:H102,"Not Started") -> 9 | H12: =IF(C12=0,0,D12/C12) -> 0
A13: 6 | B13: First Paying School | C13: =COUNTIF('Roadmap Tasks'!B2:B102,"6") -> 15 | D13: =COUNTIFS('Roadmap Tasks'!B2:B102,"6",'Roadmap Tasks'!H2:H102,"Done") -> 0 | E13: =COUNTIFS('Roadmap Tasks'!B2:B102,"6",'Roadmap Tasks'!H2:H102,"In Progress") -> 0 | F13: =COUNTIFS('Roadmap Tasks'!B2:B102,"6",'Roadmap Tasks'!H2:H102,"Blocked") -> 0 | G13: =COUNTIFS('Roadmap Tasks'!B2:B102,"6",'Roadmap Tasks'!H2:H102,"Not Started") -> 15 | H13: =IF(C13=0,0,D13/C13) -> 0
A14: TOTAL | C14: =SUM(C7:C13) -> 101 | D14: =SUM(D7:D13) -> 6 | E14: =SUM(E7:E13) -> 7 | F14: =SUM(F7:F13) -> 0 | G14: =SUM(G7:G13) -> 88 | H14: =IF(C14=0,0,D14/C14) -> 0.059405941
A16: Key Milestones
A17: Milestone | B17: Target Date | C17: Phase
A18: LLC formed + iKeepSafe intake submitted | B18: 46188 | C18: 0
A19: Migration 002 in prod (security holes closed) | B19: 46209 | C19: 1
A20: Legal documents live (privacy, ToS, NY Parent BoR, DPA template) | B20: 46244 | C20: 1
A21: Google + Sign in with Apple SSO live | B21: 46258 | C21: 2
A22: Clever Secure Sync certified | B22: 46293 | C22: 2
A23: First pilot DPA signed | B23: 46328 | C23: 4
A24: Pilot kickoff (mid-September 2026) | B24: 46279 | C24: 4
A25: iOS + Android in internal testing | B25: 46342 | C25: 3
A26: WCAG 2.1 AA audit + remediation done | B26: 46328 | C26: 2
A27: Pen test report + remediation done | B27: 46384 | C27: 4
A28: iKeepSafe COPPA cert granted | B28: 46370 | C28: 4
A29: Apple App Store approval | B29: 46454 | C29: 5
... A31: First signed paid contract (2027-28 school year) | B31: 46496 | C31: 6

Sheet Who Does What
A1: Who can do what
A2: Counts pulled by formula from the Roadmap Tasks sheet.
A4: Owner Category | B4: Task Count | C4: What it means
A5: Claude — fully complete | B5: =COUNTIF('Roadmap Tasks'!E2:E102,"Claude") -> 25 | C5: Claude can do this start to finish. The output is a file in the repo.
A6: Claude (draft) → Attorney | B6: =COUNTIF('Roadmap Tasks'!E2:E102,"*Claude (draft) → Attorney*") -> 4 | C6: Claude has drafted; attorney must review before publication.
A7: Claude (draft) → Kaelan | B7: =COUNTIF('Roadmap Tasks'!E2:E102,"*Claude (draft) → Kaelan*") -> 1 | C7: Claude has drafted; Kaelan needs to finalize, sign, or publish.
A8: Claude + Kaelan | B8: =COUNTIF('Roadmap Tasks'!E2:E102,"*Claude + Kaelan*") -> 11 | C8: Claude scaffolds code; Kaelan deploys, integrates, or tests on a device.
A9: Kaelan (Claude: code support) | B9: =COUNTIF('Roadmap Tasks'!E2:E102,"*Claude: code support*") -> 5 | C9: Kaelan owns the external setup (Google Cloud, Apple Dev, Clever); Claude can write integration code once configured.
A10: Kaelan only | B10: =COUNTIF('Roadmap Tasks'!E2:E102,"Kaelan") -> 33 | C10: Requires Kaelan's accounts, decisions, or vendor relationships. Claude cannot do this.
A11: Kaelan + Attorney | B11: =COUNTIF('Roadmap Tasks'!E2:E102,"*Kaelan + Attorney*") -> 3 | C11: Requires Kaelan's involvement plus legal review/signature.
A12: External vendor | B12: =COUNTIF('Roadmap Tasks'!E2:E102,"*External vendor*") -> 1 | C12: Requires a hired vendor (pen test, accessibility audit).
A14: Status counts
A15: Status | B15: Count
A16: Done | B16: =COUNTIF('Roadmap Tasks'!H2:H102,"Done") -> 6
A17: In Progress | B17: =COUNTIF('Roadmap Tasks'!H2:H102,"In Progress") -> 7
A18: Blocked | B18: =COUNTIF('Roadmap Tasks'!H2:H102,"Blocked") -> 0
A19: Not Started | B19: =COUNTIF('Roadmap Tasks'!H2:H102,"Not Started") -> 88
A20: Deferred | B20: =COUNTIF('Roadmap Tasks'!H2:H102,"Deferred") -> 0
A22: What Claude completed in this session
A23: RN-8 — Mobile architecture decision (Capacitor) documented in roadmap.
A24: RN-10 — Star Store positioning brief shipped at docs/star-store-positioning.md.
A25: RN-14 — Student parent-invite UI at app/dashboard/student/invite-parent/page.tsx.
A26: RN-15 — Parent redeem UI rewritten at app/parent/link/page.tsx.
A27: RN-16 — Account deletion UI at app/dashboard/settings/delete-account/page.tsx.
A28: RN-17 — Hard-delete cron worker at app/api/cron/hard-delete-accounts/route.ts + vercel.json.
A29: RN-29 — Rate-limit middleware at lib/rate-limit.ts; wired into 3 public routes.
A30: Legal drafts under legal/ (Privacy, ToS, Children's Notice, NY Parent BoR, Sub-processors, DPA checklist).
A31: Migration file at supabase/migrations/002_security_hardening.sql.
A32: Companion API routes for parent-link (code), parent-link (redeem), account deletion.

Sheet Roadmap Tasks
A1: ID | B1: Phase | C1: Category | D1: Task | E1: Owner | F1: Start | G1: Target End | H1: Status | I1: Depends On | J1: Notes
A2: RN-1 | B2: 0 | C2: Legal/Ops | D2: Form Resolution Nation LLC (NY) and register publication | E2: Kaelan | F2: 46174 | G2: 46188 | H2: Not Started | J2: ~$200 plus NY publication.
A3: RN-2 | B3: 0 | C3: Legal/Ops | D3: Open business bank account (Mercury or local) | E3: Kaelan | F3: 46174 | G3: 46188 | H3: Not Started | I3: RN-1
A4: RN-3 | B4: 0 | C4: Legal/Ops | D4: Retain ed-tech attorney (60-min scoping call) | E4: Kaelan | F4: 46174 | G4: 46188 | H4: Not Started | J4: Find someone with NYC DOE filing experience.
A5: RN-4 | B5: 0 | C5: Infra | D5: Split Supabase: staging-resolutionnation + prod-resolutionnation | E5: Kaelan | F5: 46174 | G5: 46181 | H5: Not Started | J5: Rotate service-role keys. Enable PITR on prod.
A6: RN-5 | B6: 0 | C6: Infra | D6: GitHub org + branch protection + Dependabot + secret scanning | E6: Kaelan | F6: 46174 | G6: 46181 | H6: Not Started
A7: RN-6 | B7: 0 | C7: Infra | D7: Sentry project with PII scrubbing rules | E7: Kaelan (Claude: scrubbing rules) | F7: 46174 | G7: 46188 | H7: Not Started | J7: Claude can write Sentry beforeSend filters when project exists.
A8: RN-7 | B8: 0 | C8: Compliance | D8: Submit iKeepSafe COPPA Safe Harbor intake questionnaire | E8: Kaelan | F8: 46174 | G8: 46181 | H8: Not Started | J8: Long lead time; start clock now.
A9: RN-8 | B9: 0 | C9: Product | D9: Decide mobile architecture (Capacitor vs Expo) | E9: Kaelan (Claude: recommendation locked = Capacitor) | F9: 46181 | G9: 46195 | H9: Done | J9: Decision documented in the production roadmap; Capacitor chosen.
A10: RN-9 | B10: 0 | C10: Compliance | D10: Confirm Supabase region (US East) and Anthropic data terms (zero retention) | E10: Kaelan | F10: 46174 | G10: 46188 | H10: Not Started | J10: Both go into the sub-processor disclosure.
A11: RN-10 | B11: 0 | C11: Product | D11: Document Star Store positioning: stars are earned, never purchased | E11: Claude | F11: 46188 | G11: 46195 | H11: Done | J11: Brief shipped at docs/star-store-positioning.md.
A12: RN-11 | B12: 1 | C12: Security | D12: Apply 002_security_hardening.sql migration to staging | E12: Kaelan (Claude: 002_security_hardening.sql ready) | F12: 46188 | G12: 46195 | H12: Not Started | I12: RN-4 | J12: Migration file authored by Claude. Kaelan applies to staging.
A13: RN-12 | B13: 1 | C13: Security | D13: Smoke-test new RPCs: award_stars, spend_stars, parent link, deletion | E13: Kaelan | F13: 46195 | G13: 46202 | H13: Not Started | I13: RN-11
A14: RN-13 | B14: 1 | C14: Security | D14: Apply 002_security_hardening.sql migration to prod | E14: Kaelan | F14: 46202 | G14: 46209 | H14: Not Started | I14: RN-12
A15: RN-14 | B15: 1 | C15: Product | D15: UI for student-generated parent invite code | E15: Claude | F15: 46195 | G15: 46209 | H15: Done | I15: RN-12 | J15: Shipped: app/dashboard/student/invite-parent/page.tsx.
A16: RN-15 | B16: 1 | C16: Product | D16: UI for parent enters code to link | E16: Claude | F16: 46195 | G16: 46209 | H16: Done | I16: RN-12 | J16: Shipped: app/parent/link/page.tsx (rewritten for code flow).
A17: RN-16 | B17: 1 | C17: Product | D17: UI for account deletion request and cancel (Settings) | E17: Claude | F17: 46195 | G17: 46216 | H17: Done | I17: RN-12 | J17: Shipped: app/dashboard/settings/delete-account/page.tsx.
A18: RN-17 | B18: 1 | C18: Product | D18: Scheduled job: hard-delete accounts past 30-day window | E18: Claude | F18: 46209 | G18: 46230 | H18: Done | I18: RN-16 | J18: Shipped: app/api/cron/hard-delete-accounts/route.ts + vercel.json cron config.
A19: RN-18 | B19: 1 | C19: Legal | D19: Privacy Policy published (covers FERPA, COPPA, CCPA, Ed Law 2-d) | E19: Claude (draft) → Attorney | F19: 46188 | G19: 46216 | H19: In Progress | I19: RN-3 | J19: Draft at legal/privacy-policy.md. Attorney review required.
A20: RN-19 | B20: 1 | C20: Legal | D20: Terms of Service (teacher/school + parent/student) | E20: Claude (draft) → Attorney | F20: 46188 | G20: 46216 | H20: In Progress | I20: RN-3 | J20: Draft at legal/terms-of-service.md.
A21: RN-20 | B21: 1 | C21: Legal | D21: Children's Privacy Notice (plain language) | E21: Claude (draft) → Attorney | F21: 46188 | G21: 46216 | H21: In Progress | I21: RN-3 | J21: Draft at legal/childrens-privacy-notice.md.
A22: RN-21 | B22: 1 | C22: Legal | D22: NY Parent Bill of Rights for Data Privacy and Security | E22: Claude (draft) → Attorney | F22: 46188 | G22: 46216 | H22: In Progress | I22: RN-3 | J22: Draft at legal/ny-parent-bill-of-rights.md.
A23: RN-22 | B23: 1 | C23: Legal | D23: DPA template from SDPC NDPA + NY Exhibit E | E23: Kaelan + Attorney (Claude: checklist) | F23: 46202 | G23: 46244 | H23: In Progress | I23: RN-3 | J23: Use SDPC NDPA v1r6 + NY Exhibit E. Pre-execution checklist at legal/dpa-checklist.md.
A24: RN-23 | B24: 1 | C24: Legal | D24: Publish sub-processor list on website | E24: Claude (draft) → Kaelan | F24: 46195 | G24: 46216 | H24: In Progress | I24: RN-9 | J24: Draft at legal/subprocessors.md. Add email/push providers once chosen.
A25: RN-24 | B25: 1 | C25: Compliance | D25: Parental consent flow: school-track + direct-to-family-track | E25: Claude + Kaelan | F25: 46202 | G25: 46244 | H25: Not Started | I25: RN-18 | J25: Claude can scaffold the consent flow; Kaelan picks the verification method.
A26: RN-25 | B26: 1 | C26: Compliance | D26: Age-gate at signup; route under-13 to parent consent if no school pod | E26: Claude + Kaelan | F26: 46202 | G26: 46244 | H26: Not Started | I26: RN-24
A27: RN-26 | B27: 1 | C27: Compliance | D27: Parental data export (JSON download of child's stored data) | E27: Claude + Kaelan | F27: 46209 | G27: 46258 | H27: Not Started | I27: RN-24
A28: RN-27 | B28: 1 | C28: Compliance | D28: Data minimization audit (walk every column; drop unneeded fields) | E28: Claude + Kaelan | F28: 46202 | G28: 46230 | H28: Not Started
A29: RN-28 | B29: 1 | C29: Security | D29: Encrypt sensitive PII at application layer (names + academic data) | E29: Claude + Kaelan | F29: 46209 | G29: 46244 | H29: Not Started | J29: Server-side key, quarterly rotation.
A30: RN-29 | B30: 1 | C30: Security | D30: Rate-limit all public API routes | E30: Claude | F30: 46202 | G30: 46223 | H30: In Progress | J30: Shipped: lib/rate-limit.ts + applied to parent-link, code, account-delete routes. Other API routes still need it.
A31: RN-30 | B31: 1 | C31: Security | D31: Incident response plan + 7-day NY breach notification SOP documented | E31: Claude (draft) + Kaelan | F31: 46230 | G31: 46258 | H31: Not Started
A32: RN-31 | B32: 1 | C32: Compliance | D32: Scope a focused web + mobile pen test for late Phase 4 | E32: Kaelan (Claude: code support) | F32: 46230 | G32: 46258 | H32: Not Started | J32: Needs Google Cloud project + OAuth setup.
A33: RN-32 | B33: 2 | C33: Auth | D33: Google for Education SSO (Supabase Auth Google provider) | E33: Kaelan (Claude: code support) | F33: 46209 | G33: 46244 | H33: Not Started | I33: RN-12 | J33: Needs Apple Developer Sign In with Apple service ID.
A34: RN-33 | B34: 2 | C34: Auth | D34: Sign in with Apple | E34: Kaelan (Claude: code support) | F34: 46223 | G34: 46258 | H34: Not Started | I34: RN-31 | J34: Needs Microsoft Entra app registration.
A35: RN-34 | B35: 2 | C35: Auth | D35: Microsoft / Entra ID SSO | E35: Kaelan (Claude: code support) | F35: 46230 | G35: 46279 | H35: Not Started | I35: RN-31 | J35: Clever app must be registered by Kaelan; Claude can write integration code.
A36: RN-35 | B36: 2 | C36: Rostering | D36: Clever Secure Sync integration (SSO + roster) | E36: Kaelan (Claude: code support) | F36: 46230 | G36: 46293 | H36: Not Started | I36: RN-31 | J36: Allow 4-6 weeks for Clever app certification.
A37: RN-36 | B37: 2 | C37: Rostering | D37: ClassLink integration (post-Clever) | E37: Claude | F37: 46265 | G37: 46314 | H37: Not Started | I37: RN-34
A38: RN-37 | B38: 2 | C38: Rostering | D38: CSV bulk roster import (fallback for non-Clever schools) | E38: Claude | F38: 46223 | G38: 46258 | H38: Not Started
A39: RN-38 | B39: 2 | C39: Product | D39: Teacher dashboard (class mastery, stalled roadmaps, parents linked) | E39: Claude | F39: 46230 | G39: 46286 | H39: Not Started
A40: RN-39 | B40: 2 | C40: Product | D40: Bulk student account provisioning (CSV or Clever) | E40: Claude | F40: 46244 | G40: 46286 | H40: Not Started | I40: RN-36 | J40: Extend migration 002 pattern; rotate invite_code on use.
A41: RN-40 | B41: 2 | C41: Product | D41: Rotating class invite codes (replace static pod invite_code) | E41: Claude | F41: 46230 | G41: 46265 | H41: Not Started
A42: RN-41 | B42: 2 | C42: Product | D42: Teacher-initiated parent invites (inside a class context) | E42: Claude | F42: 46230 | G42: 46265 | H42: Not Started | I42: RN-14
A43: RN-42 | B43: 2 | C43: Product | D43: Teacher data export for parent conferences (PDF + CSV) | E43: Claude | F43: 46258 | G43: 46293 | H43: Not Started | I43: RN-37
A44: RN-43 | B44: 2 | C44: Product | D44: Student archive flow (end of year) | E44: Claude | F44: 46279 | G44: 46314 | H44: Not Started
A45: RN-44 | B45: 2 | C45: Product | D45: Gift-sending guardrails (teacher visibility, optional approval) | E45: External a11y reviewer + Kaelan (Claude: pre-review) | F45: 46258 | G45: 46293 | H45: Not Started
A46: RN-45 | B46: 2 | C46: Accessibility | D46: WCAG 2.1 AA audit (color, keyboard, screen-reader, captions, motion) | E46: Claude | F46: 46265 | G46: 46314 | H46: Not Started | J46: Required by ADA Title II (Apr 2026).
A47: RN-46 | B47: 2 | C47: Accessibility | D47: Remediate WCAG findings | E47: Claude | F47: 46293 | G47: 46328 | H47: Not Started | I47: RN-44
A48: RN-47 | B48: 2 | C48: AI | D48: Server-only Anthropic goal-generation pipeline | E48: Claude | F48: 46230 | G48: 46279 | H48: Not Started | I48: RN-9 | J48: PII stripped before sending.
A49: RN-48 | B49: 2 | C49: AI | D49: Teacher approval gate before AI goals appear in student roadmaps | E49: Claude | F49: 46244 | G49: 46286 | H49: Not Started | I49: RN-46 | J49: Product cannot autonomously assign goals.
A50: RN-49 | B50: 2 | C50: AI | D50: AI call audit log: actor, prompt summary, response summary, cost | E50: Kaelan | F50: 46244 | G50: 46286 | H50: Not Started | I50: RN-46 | J50: Surface in district review pack.
A51: RN-50 | B51: 3 | C51: Stores | D51: Apple Developer Program enrollment as LLC ($99/yr) | E51: Kaelan | F51: 46188 | G51: 46223 | H51: Not Started | I51: RN-1 | J51: Allow 1-2 weeks entity verification. Start D-U-N-S in parallel.
A52: RN-51 | B52: 3 | C52: Stores | D52: Google Play Console developer account enrollment ($25) | E52: Claude + Kaelan | F52: 46188 | G52: 46223 | H52: Not Started | I52: RN-1 | J52: Claude can add Capacitor + config; Kaelan needs Xcode/Android Studio locally.
A53: RN-52 | B53: 3 | C53: Mobile | D53: Add Capacitor to Next.js project; configure ATS for own domains | E53: Claude + Kaelan | F53: 46237 | G53: 46279 | H53: Not Started | I53: RN-8 | J53: Claude wires plugins; Kaelan runs on device.
A54: RN-53 | B54: 3 | C54: Mobile | D54: Capacitor plugins: status bar, splash, icons, push, camera, share, in-app browser | E54: Claude + Kaelan | F54: 46265 | G54: 46314 | H54: Not Started | I54: RN-51
A55: RN-54 | B55: 3 | C55: Mobile | D55: APNs + FCM push notifications wired end-to-end | E55: Claude + Kaelan | F55: 46279 | G55: 46328 | H55: Not Started | I55: RN-52
A56: RN-55 | B56: 3 | C56: Mobile | D56: Universal links / app links for SSO returns | E56: Claude | F56: 46265 | G56: 46314 | H56: Not Started | I56: RN-51
A57: RN-56 | B57: 3 | C57: Mobile | D57: Deep links: invite codes open straight to consent flow | E57: Claude | F57: 46279 | G57: 46328 | H57: Not Started | I57: RN-51
A58: RN-57 | B58: 3 | C58: Mobile | D58: Offline state for student experience (no blank-screen failures) | E58: Claude | F58: 46279 | G58: 46328 | H58: Not Started | I58: RN-51
A59: RN-58 | B59: 3 | C59: Mobile | D59: Remove every 3p SDK that fails Kids Category review | E59: Claude | F59: 46293 | G59: 46328 | H59: Not Started | I59: RN-51 | J59: No Facebook, no ad SDKs, no third-party analytics.
A60: RN-59 | B60: 3 | C60: Mobile | D60: Parental gate for any external link or share/rate prompt | E60: Claude (draft) + Kaelan | F60: 46293 | G60: 46328 | H60: Not Started | I60: RN-51 | J60: Real math gate, not a dialog.
A61: RN-60 | B61: 3 | C61: Mobile | D61: Privacy nutrition labels + Google Data Safety drafts | E61: Kaelan | F61: 46314 | G61: 46342 | H61: Not Started | I61: RN-59 | J61: Requires physical iPad + Kaelan's Apple ID.
A62: RN-61 | B62: 3 | C62: Mobile | D62: iOS build runs on real iPad in TestFlight | E62: Kaelan | F62: 46314 | G62: 46342 | H62: Not Started | I62: RN-52 | J62: Requires physical device + Kaelan's Play Console.
A63: RN-62 | B63: 3 | C63: Mobile | D63: Android build runs on Pixel + Chromebook in Internal Testing | E63: Kaelan | F63: 46314 | G63: 46342 | H63: Not Started | I63: RN-52
A64: RN-63 | B64: 4 | C64: GTM | D64: Identify 3 pilot teachers from TEP / friendly NY schools | E64: Kaelan + Attorney | F64: 46244 | G64: 46293 | H64: Not Started
A65: RN-64 | B65: 4 | C65: Legal | D65: Sign first pilot DPA (SDPC NDPA + NY Exhibit E) | E65: Claude (draft) + Kaelan | F65: 46293 | G65: 46328 | H65: Not Started | I65: RN-22, RN-63
A66: RN-65 | B66: 4 | C66: GTM | D66: Pilot agreement (scope, success metrics, feedback cadence) | E66: Kaelan | F66: 46293 | G66: 46328 | H66: Not Started | I66: RN-63
A67: RN-66 | B67: 4 | C67: GTM | D67: Pilot kickoff (Monday in mid-September) | E67: Kaelan | F67: 46279 | G67: 46293 | H67: Not Started | I67: RN-64, RN-65
A68: RN-67 | B68: 4 | C68: Compliance | D68: iKeepSafe COPPA Safe Harbor — submit application package | E68: Kaelan | F68: 46279 | G68: 46328 | H68: Not Started | I68: RN-7, RN-18 | J68: $5k-$10k.
A69: RN-68 | B69: 4 | C69: Compliance | D69: iKeepSafe FERPA certification (bundle with COPPA if possible) | E69: Kaelan + Attorney | F69: 46279 | G69: 46370 | H69: Not Started | I69: RN-67
A70: RN-69 | B70: 4 | C70: Compliance | D70: NYC DOE Data Privacy & Security Vendor submission | E70: Claude (draft) + Kaelan | F70: 46279 | G70: 46349 | H70: Not Started | I70: RN-22
A71: RN-70 | B71: 4 | C71: Compliance | D71: Common Sense Privacy evaluation submitted | E71: Kaelan | F71: 46293 | G71: 46349 | H71: Not Started | I71: RN-18
A72: RN-71 | B72: 4 | C72: Compliance | D72: SDPC directory listing once NDPA signed | E72: External vendor | F72: 46328 | G72: 46370 | H72: Not Started | I72: RN-63
A73: RN-72 | B73: 4 | C73: Security | D73: Penetration test commissioned | E73: Claude + Kaelan | F73: 46293 | G73: 46349 | H73: Not Started | I73: RN-30 | J73: Triage and remediation; Claude codes fixes once findings come in.
A74: RN-73 | B74: 4 | C74: Security | D74: Pen test findings remediated (high/critical) | E74: Claude (draft) + Kaelan | F74: 46349 | G74: 46384 | H74: Not Started | I74: RN-72
A75: RN-74 | B75: 4 | C75: Compliance | D75: Security evidence pack assembled (binder for district CTOs) | E75: Kaelan | F75: 46314 | G75: 46370 | H75: Not Started
A76: RN-75 | B76: 4 | C76: Ops | D76: Status page + uptime monitoring with paging | E76: Kaelan | F76: 46314 | G76: 46349 | H76: Not Started | J76: Better Stack, Statuspage, or instatus.
A77: RN-76 | B77: 4 | C77: Ops | D77: Support inbox with published SLA + auto-reply | E77: Claude (template) + Kaelan | F77: 46314 | G77: 46349 | H77: Not Started
A78: RN-77 | B78: 4 | C78: Ops | D78: Public changelog / release notes page | E78: Kaelan | F78: 46314 | G78: 46349 | H78: Not Started
A79: RN-78 | B79: 5 | C79: Stores | D79: Apple App Store submission v1.0 | E79: Kaelan | F79: 46349 | G79: 46384 | H79: Not Started | I79: RN-59, RN-60 | J79: Expect 1-3 rejection cycles.
A80: RN-79 | B80: 5 | C80: Stores | D80: Respond to Apple review feedback; resubmit as needed | E80: Apple | F80: 46370 | G80: 46426 | H80: Not Started | I80: RN-77
A81: RN-80 | B81: 5 | C81: Stores | D81: Apple App Store approval | E81: Kaelan | F81: 46384 | G81: 46454 | H81: Not Started | I81: RN-78 | J81: Milestone.
A82: RN-81 | B82: 5 | C82: Stores | D82: Google Play submission v1.0 (Closed → Open → Production) | E82: Kaelan | F82: 46349 | G82: 46384 | H82: Not Started | I82: RN-59, RN-61
A83: RN-82 | B83: 5 | C83: Stores | D83: Designed for Families attestation submitted | E83: Kaelan | F83: 46349 | G83: 46384 | H83: Not Started | I83: RN-80
A84: RN-83 | B84: 5 | C84: Stores | D84: Respond to Google review feedback; resubmit as needed | E84: Google | F84: 46370 | G84: 46426 | H84: Not Started | I84: RN-80
A85: RN-84 | B85: 5 | C85: Stores | D85: Google Play approval | E85: Claude (scaffold) + Kaelan | F85: 46384 | G85: 46454 | H85: Not Started | I85: RN-82 | J85: Milestone.
A86: RN-85 | B86: 5 | C86: Ops | D86: Fastlane / EAS automated build pipeline for both stores | E86: Claude (draft) + Kaelan | F86: 46349 | G86: 46398 | H86: Not Started | I86: RN-77, RN-80
A87: RN-86 | B87: 5 | C87: Ops | D87: Versioning + rollback runbook | E87: Kaelan | F87: 46370 | G87: 46398 | H87: Not Started | I87: RN-84
A88: RN-87 | B88: 6 | C88: GTM | D88: Mid-pilot check-in (month 4 of pilot) | E88: Claude (draft) + Kaelan | F88: 46398 | G88: 46419 | H88: Not Started | I88: RN-66
A89: RN-88 | B89: 6 | C89: GTM | D89: Pilot outcome report (anonymized data + stories) | E89: Kaelan | F89: 46426 | G89: 46447 | H89: Not Started | I89: RN-86
A90: RN-89 | B90: 6 | C90: GTM | D90: Renewal conversation with pilot school (Feb 2027) | E90: Kaelan | F90: 46419 | G90: 46454 | H90: Not Started | I90: RN-87 | J90: Schools budget in spring.
A91: RN-90 | B91: 6 | C91: GTM | D91: Signed annual contract for 2027-28 school year | E91: Kaelan (Claude: runbook) | F91: 46447 | G91: 46496 | H91: Not Started | I91: RN-88 | J91: FIRST REVENUE.
A92: RN-91 | B92: 6 | C92: Ops | D92: Backup/restore drill #1 | E92: Kaelan (Claude: runbook) | F92: 46370 | G92: 46398 | H92: Not Started | J92: Quarterly thereafter.
A93: RN-92 | B93: 6 | C93: Ops | D93: Key rotation calendar set up (service-role quarterly) | E93: Claude (drafts) + Kaelan | F93: 46370 | G93: 46398 | H93: Not Started | J93: Claude can draft all help articles.
A94: RN-93 | B94: 6 | C94: Ops | D94: Help center: 20-30 short articles + Loom videos | E94: Kaelan | F94: 46370 | G94: 46454 | H94: Not Started
A95: RN-94 | B95: 6 | C95: Ops | D95: Monthly check-in with pilot lead teacher + principal | E95: Kaelan | F95: 46328 | G95: 46539 | H95: Not Started | I95: RN-66
A96: RN-95 | B96: 6 | C96: Compliance | D96: Decide SOC 2 path (Type I now or Type II in Year 2) | E96: Kaelan | F96: 46419 | G96: 46454 | H96: Not Started
A97: RN-96 | B97: 6 | C97: Compliance | D97: Choose compliance automation tool (Vanta / Drata / Secureframe) | E97: Claude | F97: 46370 | G97: 46419 | H97: Not Started | I97: RN-94
A98: RN-97 | B98: 6 | C98: Tech Debt | D98: Move PDF/CSV processing into a queued worker | E98: Claude | F98: 46426 | G98: 46496 | H98: Not Started | I98: RN-48
A99: RN-98 | B99: 6 | C99: Tech Debt | D99: Materialized views for teacher dashboards | E99: Claude | F99: 46426 | G99: 46496 | H99: Not Started | I99: RN-37
A100: RN-99 | B100: 6 | C100: Tech Debt | D100: Split service-role surface; prefer RPCs over admin client | E100: Claude + Kaelan | F100: 46426 | G100: 46496 | H100: Not Started
...

Sheet Compliance
A1: Artifact / Cert | B1: Authority | C1: Required For | D1: Target Date | E1: Status | F1: Cost (est.) | G1: Owner | H1: Evidence Location | I1: Notes
A2: Privacy Policy | B2: Self-published | C2: All school sales | D2: 46216 | E2: Not Started | F2: $1-3k legal | G2: Attorney + Kaelan | H2: /legal/privacy | I2: Covers FERPA, COPPA, CCPA, NY Ed Law 2-d.
A3: Terms of Service | B3: Self-published | C3: All users | D3: 46216 | E3: Not Started | F3: $1-3k legal | G3: Attorney + Kaelan | H3: /legal/terms | I3: Separate teacher/school + parent/student.
A4: Children's Privacy Notice | B4: Self-published | C4: Schools + parents | D4: 46216 | E4: Not Started | F4: Included in legal | G4: Attorney + Kaelan | H4: /legal/childrens-privacy
A5: NY Parent Bill of Rights | B5: NYSED | C5: Any NY school | D5: 46216 | E5: Not Started | F5: Template | G5: Attorney + Kaelan | H5: /legal/ny-parent-bill | I5: Ed Law 2-d §121.3.
A6: DPA template (SDPC NDPA + NY Exhibit E) | B6: SDPC + NYSED | C6: Every NY contract | D6: 46244 | E6: Not Started | F6: Attorney review $2-5k | G6: Attorney + Kaelan | H6: /legal/dpa
A7: Sub-processor list (Supabase, Vercel, Anthropic, Sentry...) | B7: Self-published | C7: All districts | D7: 46216 | E7: Not Started | F7: — | G7: Kaelan | H7: /legal/subprocessors
A8: Parental consent flow (in-product) | B8: COPPA | C8: Direct-to-family signups | D8: 46244 | E8: Not Started | F8: Engineering time | G8: Kaelan | H8: Product: signup
A9: Audit log (in-product) | B9: FERPA / Ed Law 2-d | C9: All districts | D9: 46209 | E9: Not Started | F9: Engineering time | G9: Kaelan | H9: DB: audit_log | I9: Shipped in migration 002.
A10: Account deletion (in-product) | B10: Apple / Google / FERPA | C10: App Store + district reviews | D10: 46216 | E10: Not Started | F10: Engineering time | G10: Kaelan | H10: Settings → Delete account | I10: Shipped in migration 002 + /api/account/delete.
A11: Data export (parental access) | B11: FERPA / Ed Law 2-d | C11: Districts + parents | D11: 46258 | E11: Not Started | F11: Engineering time | G11: Kaelan | H11: Settings → Export my data
A12: Incident response plan | B12: Ed Law 2-d | C12: All NY districts | D12: 46258 | E12: Not Started | F12: Template | G12: Kaelan | H12: Internal runbook | I12: 7-day NY breach notification.
A13: Penetration test report | B13: Best practice + DPA asks | C13: Districts + iKeepSafe | D13: 46384 | E13: Not Started | F13: $5-15k | G13: External vendor | H13: Internal
A14: iKeepSafe COPPA Safe Harbor certification | B14: iKeepSafe | C14: All districts | D14: 46328 | E14: Not Started | F14: $5-10k | G14: Kaelan | H14: Cert page | I14: Submit intake Phase 0.
A15: iKeepSafe FERPA certification | B15: iKeepSafe | C15: All districts | D15: 46370 | E15: Not Started | F15: $5-10k | G15: Kaelan | H15: Cert page | I15: Bundle with COPPA if possible.
A16: NYC DOE Data Privacy submission | B16: NYC DOE | C16: Any NYC public school | D16: 46349 | E16: Not Started | F16: $500-1.5k attorney | G16: Kaelan + Attorney | H16: DOE portal | I16: VendorHotline@schools.nyc.gov.
A17: Common Sense Privacy evaluation | B17: Common Sense | C17: Parents + districts | D17: 46349 | E17: Not Started | F17: Free | G17: Kaelan | H17: commonsense.org listing
A18: SDPC directory listing | B18: SDPC | C18: All districts | D18: 46370 | E18: Not Started | F18: Free | G18: Kaelan | H18: sdpc.a4l.org | I18: Requires signed NDPA first.
A19: VPAT (WCAG 2.1 AA conformance statement) | B19: Self-attested | C19: Districts + ADA | D19: 46328 | E19: Not Started | F19: $2-5k consultant | G19: Kaelan + a11y reviewer | H19: /legal/vpat
A20: Cyber liability insurance ($1M) | B20: Insurance market | C20: Before first paid contract | D20: 46454 | E20: Not Started | F20: $1-3k/yr | G20: Kaelan | H20: Policy on file | I20: Required by many districts.
A21: SOC 2 Type I (optional Year 1) | B21: AICPA | C21: Larger districts | D21: 46496 | E21: Not Started | F21: $15-30k | G21: Kaelan | H21: Auditor report | I21: Type II in Year 2.

Sheet App Store
A1: Store | B1: Category | C1: Requirement | D1: Status | E1: Notes
A2: Apple | B2: Account | C2: Apple Developer Program enrolled as LLC | D2: Not Started | E2: $99/yr.
A3: Apple | B3: Account | C3: D-U-N-S number obtained | D3: Not Started | E3: Free; can take weeks.
A4: Apple | B4: Account | C4: Two App Store Connect users (primary + backup) | D4: Not Started | E4: Avoid single-account lockout.
A5: Apple | B5: Submission | C5: Privacy nutrition labels match code reality | D5: Not Started
A6: Apple | B6: Submission | C6: Demo account credentials (sandbox, not a real teacher) | D6: Not Started
A7: Apple | B7: Submission | C7: App Review notes explaining school context + parental consent | D7: Not Started | E7: Reviewers aren't edtech specialists.
A8: Apple | B8: Required Feature | C8: In-app account deletion (Guideline 5.1.1(v)) | D8: Not Started | E8: Shipped in /api/account/delete.
A9: Apple | B9: Required Feature | C9: Sign in with Apple offered (if any 3p login present) | D9: Not Started
A10: Apple | B10: Kids Category | C10: No third-party analytics SDKs | D10: Not Started
A11: Apple | B11: Kids Category | C11: No behavioral advertising; declare zero tracking | D11: Not Started
A12: Apple | B12: Kids Category | C12: Parental gate for all external links / rate prompts | D12: Not Started | E12: Real math gate.
A13: Apple | B13: Kids Category | C13: Decide: opt into Kids Category (yes/no) | D13: Not Started | E13: Credibility vs. extra rules.
A14: Apple | B14: Build | C14: Capacitor build runs on real iPad via TestFlight | D14: Not Started
A15: Apple | B15: Assets | C15: App icons (all sizes) | D15: Not Started
A16: Apple | B16: Assets | C16: Screenshots (6.7", 6.5", 5.5", iPad 12.9") | D16: Not Started
A17: Apple | B17: Assets | C17: Promotional text + description copy | D17: Not Started
A18: Apple | B18: Pipeline | C18: Fastlane / EAS automated build | D18: Not Started
A19: Apple | B19: Pipeline | C19: Phased Release configured | D19: Not Started
A20: Google | B20: Account | C20: Play Console developer account enrolled as LLC | D20: Not Started | E20: $25 one-time.
A21: Google | B21: Account | C21: Identity verification complete | D21: Not Started | E21: Required under EU rules.
A22: Google | B22: Submission | C22: Data Safety form matches code reality | D22: Not Started | E22: Google audits this aggressively.
A23: Google | B23: Submission | C23: Target SDK level current (raised every August) | D23: Not Started
A24: Google | B24: Submission | C24: App Bundle (.aab) not APK | D24: Not Started
A25: Google | B25: Submission | C25: 64-bit support | D25: Not Started
A26: Google | B26: Required Feature | C26: In-app account deletion path (User Data policy) | D26: Not Started | E26: Shipped in /api/account/delete.
A27: Google | B27: Families | C27: Designed for Families opt-in submitted | D27: Not Started
A28: Google | B28: Families | C28: No third-party ad SDKs | D28: Not Started
A29: Google | B29: Families | C29: No behavioral analytics | D29: Not Started
A30: Google | B30: Families | C30: Age-appropriate content rating | D30: Not Started
A31: Google | B31: Build | C31: Capacitor build runs on Pixel + Chromebook (Android container) | D31: Not Started
A32: Google | B32: Assets | C32: App icon + feature graphic | D32: Not Started
A33: Google | B33: Assets | C33: Screenshots (phone + tablet) | D33: Not Started
A34: Google | B34: Assets | C34: Store listing copy | D34: Not Started
A35: Google | B35: Pipeline | C35: Closed → Open → Production rollout tracks configured | D35: Not Started

Sheet Risks
A1: # | B1: Risk | C1: Likelihood | D1: Impact | E1: Mitigation | F1: Owner | G1: Status | H1: Review By
A2: R-1 | B2: Founder burnout (solo + full-time teaching) | C2: High | D2: Severe | E2: Schedule summer build sprints + part-time sabbatical. Hire contract help by Month 9-12. Aggressive scope discipline. | F2: Kaelan | G2: Open | H2: 46354
A3: R-2 | B3: App Store rejection (Kids Category) delays pilot launch | C3: Medium | D3: Severe | E3: Design Kids Category compliance into Phase 3, not retrofit. Submit early TestFlight to surface issues. | F3: Kaelan | G3: Open | H3: 46354
A4: R-3 | B4: iKeepSafe / NYC DOE certification slower than planned | C4: High | D4: Moderate | E4: Submit intake in Phase 0/1, not Phase 4. Pilot can proceed on signed DPA before cert completes. | F4: Kaelan | G4: Open | H4: 46294
A5: R-4 | B5: Serious finding during pen test | C5: Medium | D5: High | E5: Pen test before pilot expansion not before pilot start. Budget 2-3 weeks remediation. Vendor that includes remediation guidance. | F5: Kaelan | G5: Open | H5: 46384
A6: R-5 | B6: COPPA complaint filed with FTC | C6: Low | D6: Severe | E6: iKeepSafe Safe Harbor resolution path. Robust consent + audit log makes most complaints resolvable in writing. | F6: Kaelan + Attorney | G6: Open | H6: 46354
A7: R-6 | B7: AI costs scale faster than revenue | C7: Medium | D7: Moderate | E7: Cache aggressively. Haiku for classification, Sonnet only for goal generation. Cap unit economics at $1-$2/student/year. | F7: Kaelan | G7: Open | H7: 46294
A8: R-7 | B8: Vendor questionnaire fatigue (5+ schools at once) | C8: High (after M8) | D8: Moderate | E8: Pre-fill CASBO, NDPA Exhibit E, K-12 SIX. Single source-of-truth questionnaire bank. | F8: Kaelan | G8: Open | H8: 46414
A9: R-8 | B9: Apple or Google policy change mid-build | C9: Medium | D9: Moderate | E9: Subscribe to platform developer news. Re-audit privacy declarations before every submission. | F9: Kaelan | G9: Open | H9: 46324
A10: R-9 | B10: Pilot teacher churns or moves before conversion | C10: Medium | D10: High | E10: Pilot with at least 2 teachers. Maintain principal relationship in parallel. | F10: Kaelan | G10: Open | H10: 46384
A11: R-10 | B11: Data breach | C11: Low | D11: Severe | E11: Layered controls: encryption, RLS, audit log, pen test, IR plan. Cyber liability insurance before first paid contract. | F11: Kaelan | G11: Open | H11: 46444

Sheet How to Use
A1: Resolution Nation — Roadmap Tracker
A3: How to use this workbook
A5: 1. The Dashboard sheet is the at-a-glance view. Phase counts update automatically from the Roadmap Tasks sheet.
A6: 2. Roadmap Tasks is the primary work surface. Status options are: Not Started, In Progress, Blocked, Done, Deferred. Colors are applied automatically.
A7: 3. The Compliance sheet tracks every legal artifact and certification with target dates.
A8: 4. The App Store sheet is the pre-submission checklist for Apple and Google. Work through it before each store submission.
A9: 5. The Risks sheet is reviewed monthly. Update the Review By date and the Status as risks change.
A11: Dates
A12: All target dates are anchored to a project start of 2026-06-01. If the start slips, the cleanest approach is to shift every date by the same offset; do not recompute task-by-task.
A14: Phase color legend
A15: Phase 0 — Foundation & Decisions
A16: Phase 1 — Compliance + Hardening
... A29: Compliance work is the critical path to revenue. Phase 1 in green > Phase 1 behind > everything else.
